rst2wiki.py
rst2wiki-0.3.0.dist-info/DESCRIPTION.rst
rst2wiki-0.3.0.dist-info/entry_points.txt
rst2wiki-0.3.0.dist-info/METADATA
rst2wiki-0.3.0.dist-info/metadata.json
rst2wiki-0.3.0.dist-info/RECORD
rst2wiki-0.3.0.dist-info/top_level.txt
rst2wiki-0.3.0.dist-info/WHEEL
