Metadata-Version: 2.0
Name: rst2wiki
Version: 0.3.0
Summary: Tool to push reST docs to confluence
Home-page: https://github.com/jamert/rst2wiki
Author: Artem Dayneko
Author-email: dayneko.ab@gmail.com
License: UNKNOWN
Platform: UNKNOWN
Classifier: License :: OSI Approved :: MIT License
Classifier: Programming Language :: Python
Requires-Dist: click
Requires-Dist: requests
Requires-Dist: docutils
Requires-Dist: Pygments
Requires-Dist: rst2confluence
